gaspium/__init__.py
gaspium/__main__.py
gaspium/app/.private
gaspium/app/__init__.py
gaspium/component/__init__.py
gaspium/component/button.py
gaspium/component/choice.py
gaspium/component/editor.py
gaspium/component/entry.py
gaspium/component/frame.py
gaspium/component/image.py
gaspium/component/label.py
gaspium/component/litemark.py
gaspium/component/optionmenu.py
gaspium/component/pathfield.py
gaspium/component/spinbox.py
gaspium/component/table.py
gaspium/demo/__init__.py
gaspium/demo/__main__.py
gaspium/dto/.private
gaspium/dto/__init__.py
gaspium/error/__init__.py
gaspium/misc/__init__.py
gaspium/navbar/__init__.py
gaspium/page/__init__.py
gaspium/pyrustic_data/backstage/data/build_report.json
gaspium/pyrustic_data/backstage/hooking/build.json
gaspium/pyrustic_data/backstage/hooking/init.json
gaspium/pyrustic_data/backstage/hooking/release.json
gaspium/util/.private
gaspium/util/__init__.py
tests/__init__.py
tests/__main__.py
gaspium-0.0.5.dist-info/LICENSE
gaspium-0.0.5.dist-info/METADATA
gaspium-0.0.5.dist-info/WHEEL
gaspium-0.0.5.dist-info/entry_points.txt
gaspium-0.0.5.dist-info/top_level.txt
gaspium-0.0.5.dist-info/RECORD
