Metadata-Version: 2.1
Name: gaspium
Version: 0.0.5
Summary: Framework to build Python apps with the GASP metaphor
Home-page: https://github.com/pyrustic/gaspium
Author: Pyrustic Evangelist
Author-email: rusticalex@yahoo.com
Maintainer: Pyrustic Evangelist
Maintainer-email: rusticalex@yahoo.com
License: MIT
Keywords: framework,GASP,GUI,productivity,batteries-included,apps,pages,pyrustic
Platform: UNKNOWN
Classifier: Programming Language :: Python :: 3
Classifier: License :: OSI Approved :: MIT License
Classifier: Operating System :: OS Independent
Requires-Python: >=3.5
License-File: LICENSE
Requires-Dist: viewable
Requires-Dist: viewstack
